logdot/__init__.py
logdot/http.py
logdot/logger.py
logdot/metrics.py
logdot/py.typed
logdot/types.py
logdot_io_sdk-1.0.0.dist-info/licenses/LICENSE
logdot_io_sdk-1.0.0.dist-info/METADATA
logdot_io_sdk-1.0.0.dist-info/WHEEL
logdot_io_sdk-1.0.0.dist-info/top_level.txt
logdot_io_sdk-1.0.0.dist-info/RECORD
