Metadata-Version: 2.4
Name: logdot-io-sdk
Version: 1.0.0
Summary: LogDot SDK for Python - Cloud logging and metrics
Author-email: LogDot <support@logdot.io>
License: MIT
Project-URL: Homepage, https://logdot.io
Project-URL: Documentation, https://docs.logdot.io/python
Project-URL: Repository, https://github.com/logdot-io/logdot-python
Keywords: logging,metrics,cloud,monitoring,logdot,observability,logdot-io
Classifier: Development Status :: 5 - Production/Stable
Classifier: Intended Audience :: Developers
Classifier: License :: OSI Approved :: MIT License
Classifier: Programming Language :: Python :: 3
Classifier: Programming Language :: Python :: 3.8
Classifier: Programming Language :: Python :: 3.9
Classifier: Programming Language :: Python :: 3.10
Classifier: Programming Language :: Python :: 3.11
Classifier: Programming Language :: Python :: 3.12
Classifier: Topic :: System :: Logging
Classifier: Topic :: System :: Monitoring
Requires-Python: >=3.8
License-File: LICENSE
Requires-Dist: requests>=2.25.0
Provides-Extra: dev
Requires-Dist: pytest>=7.0.0; extra == "dev"
Requires-Dist: pytest-cov>=4.0.0; extra == "dev"
Requires-Dist: mypy>=1.0.0; extra == "dev"
Requires-Dist: black>=23.0.0; extra == "dev"
Requires-Dist: responses>=0.23.0; extra == "dev"
Dynamic: license-file
